vidserve/__init__.py
vidserve/__main__.py
vidserve/cli.py
vidserve/server.py
vidserve/video_utils.py
vidserve/templates/index.html
vidserve-0.1.2.dist-info/METADATA
vidserve-0.1.2.dist-info/WHEEL
vidserve-0.1.2.dist-info/entry_points.txt
vidserve-0.1.2.dist-info/RECORD
