Metadata-Version: 2.4
Name: vidserve
Version: 0.1.2
Summary: A video serving application
Requires-Python: >=3.11
Requires-Dist: click>=8.1.0
Requires-Dist: flask>=3.0.0
Requires-Dist: gunicorn>=21.0.0
Requires-Dist: opencv-python>=4.8.0
Requires-Dist: pillow>=10.0.0
